deepread_contract/__init__.py
deepread_contract/auth.py
deepread_contract/checker.py
deepread_contract/cli.py
deepread_contract/cnpj.py
deepread_contract/keywords.py
deepread_contract/models.py
deepread_contract-0.1.0.dist-info/METADATA
deepread_contract-0.1.0.dist-info/WHEEL
deepread_contract-0.1.0.dist-info/entry_points.txt
deepread_contract-0.1.0.dist-info/licenses/LICENSE
deepread_contract-0.1.0.dist-info/RECORD
