Metadata-Version: 2.4
Name: deepread-contract
Version: 0.1.0
Summary: Biblioteca para validação de documentos e contratos brasileiros
Project-URL: Homepage, https://github.com/BeMonkAI/deepread.contract
Project-URL: Documentation, https://github.com/BeMonkAI/deepread.contract#readme
Project-URL: Repository, https://github.com/BeMonkAI/deepread.contract
Project-URL: Issues, https://github.com/BeMonkAI/deepread.contract/issues
Author-email: BeMonkAI <contato@bemonk.ai>
License-Expression: MIT
License-File: LICENSE
Keywords: brasil,cnpj,contract,document,pdf,receita-federal,validation
Classifier: Development Status :: 4 - Beta
Classifier: Intended Audience :: Developers
Classifier: Intended Audience :: Legal Industry
Classifier: License :: OSI Approved :: MIT License
Classifier: Operating System :: OS Independent
Classifier: Programming Language :: Python :: 3
Classifier: Programming Language :: Python :: 3.9
Classifier: Programming Language :: Python :: 3.10
Classifier: Programming Language :: Python :: 3.11
Classifier: Programming Language :: Python :: 3.12
Classifier: Topic :: Office/Business
Classifier: Topic :: Text Processing :: General
Requires-Python: >=3.9
Requires-Dist: pydantic>=2.0.0
Requires-Dist: requests>=2.25.0
Provides-Extra: ai
Requires-Dist: openai>=1.0.0; extra == 'ai'
Provides-Extra: dev
Requires-Dist: black>=23.0.0; extra == 'dev'
Requires-Dist: pytest-cov>=4.0.0; extra == 'dev'
Requires-Dist: pytest>=7.0.0; extra == 'dev'
Requires-Dist: ruff>=0.1.0; extra == 'dev'
